[
    {
        "title1": "Analyste informatique",
        "title2": "Solutions Novika",
        "title3": "La Pocatière",

        "subtitle": "août 2021 - août 2022",

        "description": "Concevoir et planifier le développement d'applications logicielles dans un contexte de recherche appliquée en entreprise"
    }, 
    {   
        "title1": "Manoeuvre agricole",
        "title2": "Vegpro",
        "title3": "Sherrington",

        "subtitle": "juin 2020 - août 2020",

        "description": "Travail physique nécessitant beaucoup de coordination avec les autres membres de l'équipe afin d'assurer le bon déroulement de la récolte."
    }
]